{
  "_fv": 73,
  "_type": "achievement",
  "definition": {
    "achievementName": "Have you lost your mind?",
    "achievementDescription": "Get an ice cream from a living ice cream",
    "achievementIcon": {
      "value": "CUSTOM:EmptyIceCreamCone"
    },
    "background": "Default",
    "disableDisplay": false,
    "showPopup": true,
    "announceToChat": true,
    "hideIfNotCompleted": false,
    "rewardLoot": [],
    "rewardRecipes": [],
    "rewardXP": 2,
    "achievementType": "task",
    "parent": {
      "value": "CUSTOM:IceCreamMania"
    },
    "triggerxml": "<xml xmlns=\"https://developers.google.com/blockly/xml\"><block type=\"advancement_trigger\" deletable=\"false\" x=\"40\" y=\"80\"><next><block type=\"custom_trigger\"></block></next></block></xml>"
  }
}